[H[2J[3JDisassembly of ASU:
Disassembly of __init__:
 42           0 LOAD_FAST                0 (self)
              3 LOAD_ATTR                0 (banner)
              6 CALL_FUNCTION            0
              9 POP_TOP             

 43          10 LOAD_FAST                0 (self)
             13 LOAD_ATTR                1 (choice)
             16 CALL_FUNCTION            0
             19 POP_TOP             
             20 LOAD_CONST               0 (None)
             23 RETURN_VALUE        

Disassembly of backk:
 46           0 LOAD_GLOBAL              0 (raw_input)
              3 LOAD_CONST               1 ('press enter to menu ...')
              6 CALL_FUNCTION            1
              9 POP_TOP             

 47          10 LOAD_GLOBAL              1 (ASU)
             13 CALL_FUNCTION            0
             16 POP_TOP             
             17 LOAD_CONST               0 (None)
             20 RETURN_VALUE        

Disassembly of banner:
 50           0 LOAD_GLOBAL              0 (banner)
              3 LOAD_ATTR                1 (_asu_banner)
              6 CALL_FUNCTION            0
              9 PRINT_ITEM          
             10 PRINT_NEWLINE       

 51          11 LOAD_CONST               1 ('  %s{%s88%s} Report Bug (WhatsApp) ')
             14 LOAD_GLOBAL              2 (N)
             17 LOAD_GLOBAL              3 (G)
             20 LOAD_GLOBAL              2 (N)
             23 BUILD_TUPLE              3
             26 BINARY_MODULO       
             27 PRINT_ITEM          
             28 PRINT_NEWLINE       

 52          29 LOAD_CONST               2 ('  %s{%s99%s} Tutorial (Youtube)\n\n')
             32 LOAD_GLOBAL              2 (N)
             35 LOAD_GLOBAL              3 (G)
             38 LOAD_GLOBAL              2 (N)
             41 BUILD_TUPLE              3
             44 BINARY_MODULO       
             45 PRINT_ITEM          
             46 PRINT_NEWLINE       
             47 LOAD_CONST               0 (None)
             50 RETURN_VALUE        

Disassembly of choice:
 55           0 SETUP_EXCEPT            41 (to 44)

 56           3 LOAD_GLOBAL              0 (raw_input)
              6 LOAD_CONST               1 ('%s[%s+%s]%s @deray_> ')
              9 LOAD_GLOBAL              1 (G)
             12 LOAD_GLOBAL              2 (R)
             15 LOAD_GLOBAL              1 (G)
             18 LOAD_GLOBAL              3 (N)
             21 BUILD_TUPLE              4
             24 BINARY_MODULO       
             25 CALL_FUNCTION            1
             28 LOAD_ATTR                4 (lower)
             31 CALL_FUNCTION            0
             34 LOAD_FAST                0 (self)
             37 STORE_ATTR               5 (asw)
             40 POP_BLOCK           
             41 JUMP_FORWARD            27 (to 71)

 57     >>   44 POP_TOP             
             45 POP_TOP             
             46 POP_TOP             

 58          47 LOAD_GLOBAL              6 (exit)
             50 LOAD_CONST               2 ('%s[-]%s User Interrupt.')
             53 LOAD_GLOBAL              2 (R)
             56 LOAD_GLOBAL              3 (N)
             59 BUILD_TUPLE              2
             62 BINARY_MODULO       
             63 CALL_FUNCTION            1
             66 POP_TOP             
             67 JUMP_FORWARD            26 (to 96)
             70 END_FINALLY         

 60     >>   71 LOAD_FAST                0 (self)
             74 LOAD_ATTR                5 (asw)
             77 LOAD_CONST               3 ('')
             80 COMPARE_OP               2 (==)
             83 POP_JUMP_IF_FALSE       96

 61          86 LOAD_FAST                0 (self)
             89 LOAD_ATTR                7 (choice)
             92 CALL_FUNCTION            0
             95 RETURN_VALUE        

 63     >>   96 LOAD_FAST                0 (self)
             99 LOAD_ATTR                5 (asw)
            102 LOAD_CONST               4 ('1')
            105 COMPARE_OP               2 (==)
            108 POP_JUMP_IF_TRUE       126
            111 LOAD_FAST                0 (self)
            114 LOAD_ATTR                5 (asw)
            117 LOAD_CONST               5 ('01')
            120 COMPARE_OP               2 (==)
            123 POP_JUMP_IF_FALSE      155

 64     >>  126 LOAD_CONST               6 (-1)
            129 LOAD_CONST               7 (('create_server',))
            132 IMPORT_NAME              8 (data)
            135 IMPORT_FROM              9 (create_server)
            138 STORE_FAST               1 (create_server)
            141 POP_TOP             

 65         142 LOAD_FAST                1 (create_server)
            145 LOAD_ATTR               10 (phising)
            148 CALL_FUNCTION            0
            151 POP_TOP             
            152 JUMP_FORWARD          1842 (to 1997)

 67     >>  155 LOAD_FAST                0 (self)
            158 LOAD_ATTR                5 (asw)
            161 LOAD_CONST               8 ('2')
            164 COMPARE_OP               2 (==)
            167 POP_JUMP_IF_TRUE       185
            170 LOAD_FAST                0 (self)
            173 LOAD_ATTR                5 (asw)
            176 LOAD_CONST               9 ('02')
            179 COMPARE_OP               2 (==)
            182 POP_JUMP_IF_FALSE      224

 68     >>  185 LOAD_CONST               6 (-1)
            188 LOAD_CONST              10 (('dumpper',))
            191 IMPORT_NAME              8 (data)
            194 IMPORT_FROM             11 (dumpper)
            197 STORE_FAST               2 (dumpper)
            200 POP_TOP             

 69         201 LOAD_FAST                2 (dumpper)
            204 LOAD_ATTR               12 (pilihan)
            207 CALL_FUNCTION            0
            210 POP_TOP             

 70         211 LOAD_FAST                0 (self)
            214 LOAD_ATTR               13 (backk)
            217 CALL_FUNCTION            0
            220 POP_TOP             
            221 JUMP_FORWARD          1773 (to 1997)

 72     >>  224 LOAD_FAST                0 (self)
            227 LOAD_ATTR                5 (asw)
            230 LOAD_CONST              11 ('3')
            233 COMPARE_OP               2 (==)
            236 POP_JUMP_IF_TRUE       254
            239 LOAD_FAST                0 (self)
            242 LOAD_ATTR                5 (asw)
            245 LOAD_CONST              12 ('03')
            248 COMPARE_OP               2 (==)
            251 POP_JUMP_IF_FALSE      293

 73     >>  254 LOAD_CONST               6 (-1)
            257 LOAD_CONST              13 (('spammer',))
            260 IMPORT_NAME              8 (data)
            263 IMPORT_FROM             14 (spammer)
            266 STORE_FAST               3 (spammer)
            269 POP_TOP             

 74         270 LOAD_FAST                3 (spammer)
            273 LOAD_ATTR               15 (main)
            276 CALL_FUNCTION            0
            279 POP_TOP             

 75         280 LOAD_FAST                0 (self)
            283 LOAD_ATTR               13 (backk)
            286 CALL_FUNCTION            0
            289 POP_TOP             
            290 JUMP_FORWARD          1704 (to 1997)

 77     >>  293 LOAD_FAST                0 (self)
            296 LOAD_ATTR                5 (asw)
            299 LOAD_CONST              14 ('4')
            302 COMPARE_OP               2 (==)
            305 POP_JUMP_IF_TRUE       323
            308 LOAD_FAST                0 (self)
            311 LOAD_ATTR                5 (asw)
            314 LOAD_CONST              15 ('04')
            317 COMPARE_OP               2 (==)
            320 POP_JUMP_IF_FALSE      748

 78     >>  323 LOAD_CONST              16 ('\n\t[ Select Actions ]\n')
            326 PRINT_ITEM          
            327 PRINT_NEWLINE       

 79         328 LOAD_CONST              17 ('  {%s01%s} Reports Status Target')
            331 LOAD_GLOBAL              1 (G)
            334 LOAD_GLOBAL              3 (N)
            337 BUILD_TUPLE              2
            340 BINARY_MODULO       
            341 PRINT_ITEM          
            342 PRINT_NEWLINE       

 80         343 LOAD_CONST              18 ('  {%s02%s} Mass Reports Profile')
            346 LOAD_GLOBAL              1 (G)
            349 LOAD_GLOBAL              3 (N)
            352 BUILD_TUPLE              2
            355 BINARY_MODULO       
            356 PRINT_ITEM          
            357 PRINT_NEWLINE       

 81         358 LOAD_CONST              19 ('  {%s03%s} Page Reports')
            361 LOAD_GLOBAL              1 (G)
            364 LOAD_GLOBAL              3 (N)
            367 BUILD_TUPLE              2
            370 BINARY_MODULO       
            371 PRINT_ITEM          
            372 PRINT_NEWLINE       

 82         373 LOAD_CONST              20 ('  {%s04%s} Group Reports')
            376 LOAD_GLOBAL              1 (G)
            379 LOAD_GLOBAL              3 (N)
            382 BUILD_TUPLE              2
            385 BINARY_MODULO       
            386 PRINT_ITEM          
            387 PRINT_NEWLINE       

 83         388 LOAD_CONST              21 ('  {%s05%s} Back To Menu Option')
            391 LOAD_GLOBAL              2 (R)
            394 LOAD_GLOBAL              3 (N)
            397 BUILD_TUPLE              2
            400 BINARY_MODULO       
            401 PRINT_ITEM          
            402 PRINT_NEWLINE       

 84         403 LOAD_GLOBAL              0 (raw_input)
            406 LOAD_CONST              22 ('\n%s[%s+%s] %sActions>> ')
            409 LOAD_GLOBAL              1 (G)
            412 LOAD_GLOBAL              2 (R)
            415 LOAD_GLOBAL              1 (G)
            418 LOAD_GLOBAL              3 (N)
            421 BUILD_TUPLE              4
            424 BINARY_MODULO       
            425 CALL_FUNCTION            1
            428 STORE_FAST               4 (i)

 85         431 LOAD_FAST                4 (i)
            434 LOAD_CONST               4 ('1')
            437 COMPARE_OP               2 (==)
            440 POP_JUMP_IF_TRUE       455
            443 LOAD_FAST                4 (i)
            446 LOAD_CONST               5 ('01')
            449 COMPARE_OP               2 (==)
            452 POP_JUMP_IF_FALSE      494

 86     >>  455 LOAD_CONST               6 (-1)
            458 LOAD_CONST              23 (('reportContent',))
            461 IMPORT_NAME              8 (data)
            464 IMPORT_FROM             16 (reportContent)
            467 STORE_FAST               5 (reportContent)
            470 POP_TOP             

 87         471 LOAD_FAST                5 (reportContent)
            474 LOAD_ATTR               16 (reportContent)
            477 CALL_FUNCTION            0
            480 POP_TOP             

 88         481 LOAD_FAST                0 (self)
            484 LOAD_ATTR               13 (backk)
            487 CALL_FUNCTION            0
            490 POP_TOP             
            491 JUMP_ABSOLUTE         1997

 89     >>  494 LOAD_FAST                4 (i)
            497 LOAD_CONST               8 ('2')
            500 COMPARE_OP               2 (==)
            503 POP_JUMP_IF_TRUE       518
            506 LOAD_FAST                4 (i)
            509 LOAD_CONST               9 ('02')
            512 COMPARE_OP               2 (==)
            515 POP_JUMP_IF_FALSE      557

 90     >>  518 LOAD_CONST               6 (-1)
            521 LOAD_CONST              24 (('reports',))
            524 IMPORT_NAME              8 (data)
            527 IMPORT_FROM             17 (reports)
            530 STORE_FAST               6 (reports)
            533 POP_TOP             

 91         534 LOAD_FAST                6 (reports)
            537 LOAD_ATTR               18 (report)
            540 CALL_FUNCTION            0
            543 POP_TOP             

 92         544 LOAD_FAST                0 (self)
            547 LOAD_ATTR               13 (backk)
            550 CALL_FUNCTION            0
            553 POP_TOP             
            554 JUMP_ABSOLUTE         1997

 93     >>  557 LOAD_FAST                4 (i)
            560 LOAD_CONST              11 ('3')
            563 COMPARE_OP               2 (==)
            566 POP_JUMP_IF_TRUE       581
            569 LOAD_FAST                4 (i)
            572 LOAD_CONST              12 ('03')
            575 COMPARE_OP               2 (==)
            578 POP_JUMP_IF_FALSE      620

 94     >>  581 LOAD_CONST               6 (-1)
            584 LOAD_CONST              25 (('page_report',))
            587 IMPORT_NAME              8 (data)
            590 IMPORT_FROM             19 (page_report)
            593 STORE_FAST               7 (page_report)
            596 POP_TOP             

 95         597 LOAD_FAST                7 (page_report)
            600 LOAD_ATTR               20 (reportpage)
            603 CALL_FUNCTION            0
            606 POP_TOP             

 96         607 LOAD_FAST                0 (self)
            610 LOAD_ATTR               13 (backk)
            613 CALL_FUNCTION            0
            616 POP_TOP             
            617 JUMP_ABSOLUTE         1997

 97     >>  620 LOAD_FAST                4 (i)
            623 LOAD_CONST              14 ('4')
            626 COMPARE_OP               2 (==)
            629 POP_JUMP_IF_TRUE       644
            632 LOAD_FAST                4 (i)
            635 LOAD_CONST              15 ('04')
            638 COMPARE_OP               2 (==)
            641 POP_JUMP_IF_FALSE      683

 98     >>  644 LOAD_CONST               6 (-1)
            647 LOAD_CONST              26 (('group_report',))
            650 IMPORT_NAME              8 (data)
            653 IMPORT_FROM             21 (group_report)
            656 STORE_FAST               8 (group_report)
            659 POP_TOP             

 99         660 LOAD_FAST                8 (group_report)
            663 LOAD_ATTR               22 (index)
            666 CALL_FUNCTION            0
            669 POP_TOP             

100         670 LOAD_FAST                0 (self)
            673 LOAD_ATTR               13 (backk)
            676 CALL_FUNCTION            0
            679 POP_TOP             
            680 JUMP_ABSOLUTE         1997

101     >>  683 LOAD_FAST                4 (i)
            686 LOAD_CONST              27 ('5')
            689 COMPARE_OP               2 (==)
            692 POP_JUMP_IF_TRUE       707
            695 LOAD_FAST                4 (i)
            698 LOAD_CONST              28 ('05')
            701 COMPARE_OP               2 (==)
            704 POP_JUMP_IF_FALSE      720

102     >>  707 LOAD_FAST                0 (self)
            710 LOAD_ATTR               13 (backk)
            713 CALL_FUNCTION            0
            716 POP_TOP             
            717 JUMP_ABSOLUTE         1997

104     >>  720 LOAD_CONST              29 ('%s[!]%s invalid options!')
            723 LOAD_GLOBAL              2 (R)
            726 LOAD_GLOBAL              3 (N)
            729 BUILD_TUPLE              2
            732 BINARY_MODULO       
            733 PRINT_ITEM          
            734 PRINT_NEWLINE       

105         735 LOAD_FAST                0 (self)
            738 LOAD_ATTR               13 (backk)
            741 CALL_FUNCTION            0
            744 POP_TOP             
            745 JUMP_FORWARD          1249 (to 1997)

107     >>  748 LOAD_FAST                0 (self)
            751 LOAD_ATTR                5 (asw)
            754 LOAD_CONST              27 ('5')
            757 COMPARE_OP               2 (==)
            760 POP_JUMP_IF_TRUE       778
            763 LOAD_FAST                0 (self)
            766 LOAD_ATTR                5 (asw)
            769 LOAD_CONST              28 ('05')
            772 COMPARE_OP               2 (==)
            775 POP_JUMP_IF_FALSE      817

108     >>  778 LOAD_CONST               6 (-1)
            781 LOAD_CONST              30 (('auto_addgrup',))
            784 IMPORT_NAME              8 (data)
            787 IMPORT_FROM             23 (auto_addgrup)
            790 STORE_FAST               9 (auto_addgrup)
            793 POP_TOP             

109         794 LOAD_FAST                9 (auto_addgrup)
            797 LOAD_ATTR               24 (grup)
            800 CALL_FUNCTION            0
            803 POP_TOP             

110         804 LOAD_FAST                0 (self)
            807 LOAD_ATTR               13 (backk)
            810 CALL_FUNCTION            0
            813 POP_TOP             
            814 JUMP_FORWARD          1180 (to 1997)

112     >>  817 LOAD_FAST                0 (self)
            820 LOAD_ATTR                5 (asw)
            823 LOAD_CONST              31 ('6')
            826 COMPARE_OP               2 (==)
            829 POP_JUMP_IF_TRUE       847
            832 LOAD_FAST                0 (self)
            835 LOAD_ATTR                5 (asw)
            838 LOAD_CONST              32 ('06')
            841 COMPARE_OP               2 (==)
            844 POP_JUMP_IF_FALSE      886

113     >>  847 LOAD_CONST               6 (-1)
            850 LOAD_CONST              33 (('risetPass',))
            853 IMPORT_NAME              8 (data)
            856 IMPORT_FROM             25 (risetPass)
            859 STORE_FAST              10 (risetPass)
            862 POP_TOP             

114         863 LOAD_FAST               10 (risetPass)
            866 LOAD_ATTR               25 (risetPass)
            869 CALL_FUNCTION            0
            872 POP_TOP             

115         873 LOAD_FAST                0 (self)
            876 LOAD_ATTR               13 (backk)
            879 CALL_FUNCTION            0
            882 POP_TOP             
            883 JUMP_FORWARD          1111 (to 1997)

117     >>  886 LOAD_FAST                0 (self)
            889 LOAD_ATTR                5 (asw)
            892 LOAD_CONST              34 ('7')
            895 COMPARE_OP               2 (==)
            898 POP_JUMP_IF_TRUE       916
            901 LOAD_FAST                0 (self)
            904 LOAD_ATTR                5 (asw)
            907 LOAD_CONST              35 ('07')
            910 COMPARE_OP               2 (==)
            913 POP_JUMP_IF_FALSE      945

118     >>  916 LOAD_CONST               6 (-1)
            919 LOAD_CONST               7 (('create_server',))
            922 IMPORT_NAME              8 (data)
            925 IMPORT_FROM              9 (create_server)
            928 STORE_FAST               1 (create_server)
            931 POP_TOP             

119         932 LOAD_FAST                1 (create_server)
            935 LOAD_ATTR               26 (locator)
            938 CALL_FUNCTION            0
            941 POP_TOP             
            942 JUMP_FORWARD          1052 (to 1997)

121     >>  945 LOAD_FAST                0 (self)
            948 LOAD_ATTR                5 (asw)
            951 LOAD_CONST              36 ('8')
            954 COMPARE_OP               2 (==)
            957 POP_JUMP_IF_TRUE       975
            960 LOAD_FAST                0 (self)
            963 LOAD_ATTR                5 (asw)
            966 LOAD_CONST              37 ('08')
            969 COMPARE_OP               2 (==)
            972 POP_JUMP_IF_FALSE     1004

122     >>  975 LOAD_CONST               6 (-1)
            978 LOAD_CONST               7 (('create_server',))
            981 IMPORT_NAME              8 (data)
            984 IMPORT_FROM              9 (create_server)
            987 STORE_FAST               1 (create_server)
            990 POP_TOP             

123         991 LOAD_FAST                1 (create_server)
            994 LOAD_ATTR               27 (gps)
            997 CALL_FUNCTION            0
           1000 POP_TOP             
           1001 JUMP_FORWARD           993 (to 1997)

125     >> 1004 LOAD_FAST                0 (self)
           1007 LOAD_ATTR                5 (asw)
           1010 LOAD_CONST              38 ('9')
           1013 COMPARE_OP               2 (==)
           1016 POP_JUMP_IF_TRUE      1034
           1019 LOAD_FAST                0 (self)
           1022 LOAD_ATTR                5 (asw)
           1025 LOAD_CONST              39 ('09')
           1028 COMPARE_OP               2 (==)
           1031 POP_JUMP_IF_FALSE     1073

126     >> 1034 LOAD_CONST               6 (-1)
           1037 LOAD_CONST              40 (('checkpoint_detector',))
           1040 IMPORT_NAME              8 (data)
           1043 IMPORT_FROM             28 (checkpoint_detector)
           1046 STORE_FAST              11 (checkpoint_detector)
           1049 POP_TOP             

127        1050 LOAD_FAST               11 (checkpoint_detector)
           1053 LOAD_ATTR               29 (bypass)
           1056 CALL_FUNCTION            0
           1059 POP_TOP             

128        1060 LOAD_FAST                0 (self)
           1063 LOAD_ATTR               13 (backk)
           1066 CALL_FUNCTION            0
           1069 POP_TOP             
           1070 JUMP_FORWARD           924 (to 1997)

130     >> 1073 LOAD_FAST                0 (self)
           1076 LOAD_ATTR                5 (asw)
           1079 LOAD_CONST              41 ('10')
           1082 COMPARE_OP               2 (==)
           1085 POP_JUMP_IF_FALSE     1393

131        1088 LOAD_CONST              42 ('\t[ Select Actions ]\n')
           1091 PRINT_ITEM          
           1092 PRINT_NEWLINE       

132        1093 LOAD_CONST              43 ('  {%s01%s} Akun Ceker (save to file)')
           1096 LOAD_GLOBAL              1 (G)
           1099 LOAD_GLOBAL              3 (N)
           1102 BUILD_TUPLE              2
           1105 BINARY_MODULO       
           1106 PRINT_ITEM          
           1107 PRINT_NEWLINE       

133        1108 LOAD_CONST              44 ('  {%s02%s} Akun Ceker (Just Cek)')
           1111 LOAD_GLOBAL              1 (G)
           1114 LOAD_GLOBAL              3 (N)
           1117 BUILD_TUPLE              2
           1120 BINARY_MODULO       
           1121 PRINT_ITEM          
           1122 PRINT_NEWLINE       

134        1123 LOAD_CONST              45 ('  {%s03%s} Group Cheker')
           1126 LOAD_GLOBAL              1 (G)
           1129 LOAD_GLOBAL              3 (N)
           1132 BUILD_TUPLE              2
           1135 BINARY_MODULO       
           1136 PRINT_ITEM          
           1137 PRINT_NEWLINE       

135        1138 LOAD_CONST              46 ('  {%s04%s} Back\n')
           1141 LOAD_GLOBAL              2 (R)
           1144 LOAD_GLOBAL              3 (N)
           1147 BUILD_TUPLE              2
           1150 BINARY_MODULO       
           1151 PRINT_ITEM          
           1152 PRINT_NEWLINE       

136        1153 LOAD_GLOBAL              0 (raw_input)
           1156 LOAD_CONST              47 ('\n%s[%s*%s]%s Actions>> ')
           1159 LOAD_GLOBAL              1 (G)
           1162 LOAD_GLOBAL              2 (R)
           1165 LOAD_GLOBAL              1 (G)
           1168 LOAD_GLOBAL              3 (N)
           1171 BUILD_TUPLE              4
           1174 BINARY_MODULO       
           1175 CALL_FUNCTION            1
           1178 STORE_FAST              12 (pk)

137        1181 LOAD_FAST               12 (pk)
           1184 LOAD_CONST               4 ('1')
           1187 COMPARE_OP               2 (==)
           1190 POP_JUMP_IF_TRUE      1205
           1193 LOAD_FAST               12 (pk)
           1196 LOAD_CONST               5 ('01')
           1199 COMPARE_OP               2 (==)
           1202 POP_JUMP_IF_FALSE     1244

138     >> 1205 LOAD_CONST               6 (-1)
           1208 LOAD_CONST              48 (('checker',))
           1211 IMPORT_NAME              8 (data)
           1214 IMPORT_FROM             30 (checker)
           1217 STORE_FAST              13 (checker)
           1220 POP_TOP             

139        1221 LOAD_FAST               13 (checker)
           1224 LOAD_ATTR               31 (check)
           1227 CALL_FUNCTION            0
           1230 POP_TOP             

140        1231 LOAD_FAST                0 (self)
           1234 LOAD_ATTR               13 (backk)
           1237 CALL_FUNCTION            0
           1240 POP_TOP             
           1241 JUMP_ABSOLUTE         1997

141     >> 1244 LOAD_FAST               12 (pk)
           1247 LOAD_CONST               8 ('2')
           1250 COMPARE_OP               2 (==)
           1253 POP_JUMP_IF_TRUE      1268
           1256 LOAD_FAST               12 (pk)
           1259 LOAD_CONST               9 ('02')
           1262 COMPARE_OP               2 (==)
           1265 POP_JUMP_IF_FALSE     1307

142     >> 1268 LOAD_CONST               6 (-1)
           1271 LOAD_CONST              48 (('checker',))
           1274 IMPORT_NAME              8 (data)
           1277 IMPORT_FROM             30 (checker)
           1280 STORE_FAST              13 (checker)
           1283 POP_TOP             

143        1284 LOAD_FAST               13 (checker)
           1287 LOAD_ATTR               32 (che)
           1290 CALL_FUNCTION            0
           1293 POP_TOP             

144        1294 LOAD_FAST                0 (self)
           1297 LOAD_ATTR               13 (backk)
           1300 CALL_FUNCTION            0
           1303 POP_TOP             
           1304 JUMP_ABSOLUTE         1997

145     >> 1307 LOAD_FAST               12 (pk)
           1310 LOAD_CONST              11 ('3')
           1313 COMPARE_OP               2 (==)
           1316 POP_JUMP_IF_TRUE      1331
           1319 LOAD_FAST               12 (pk)
           1322 LOAD_CONST              12 ('03')
           1325 COMPARE_OP               2 (==)
           1328 POP_JUMP_IF_FALSE     1370

146     >> 1331 LOAD_CONST               6 (-1)
           1334 LOAD_CONST              48 (('checker',))
           1337 IMPORT_NAME              8 (data)
           1340 IMPORT_FROM             30 (checker)
           1343 STORE_FAST              13 (checker)
           1346 POP_TOP             

147        1347 LOAD_FAST               13 (checker)
           1350 LOAD_ATTR               22 (index)
           1353 CALL_FUNCTION            0
           1356 POP_TOP             

148        1357 LOAD_FAST                0 (self)
           1360 LOAD_ATTR               13 (backk)
           1363 CALL_FUNCTION            0
           1366 POP_TOP             
           1367 JUMP_ABSOLUTE         1997

150     >> 1370 LOAD_GLOBAL              6 (exit)
           1373 LOAD_CONST              49 ('%s[!]%s Invalid Options.')
           1376 LOAD_GLOBAL              2 (R)
           1379 LOAD_GLOBAL              3 (N)
           1382 BUILD_TUPLE              2
           1385 BINARY_MODULO       
           1386 CALL_FUNCTION            1
           1389 POP_TOP             
           1390 JUMP_FORWARD           604 (to 1997)

152     >> 1393 LOAD_FAST                0 (self)
           1396 LOAD_ATTR                5 (asw)
           1399 LOAD_CONST              50 ('11')
           1402 COMPARE_OP               2 (==)
           1405 POP_JUMP_IF_FALSE     1447

153        1408 LOAD_CONST               6 (-1)
           1411 LOAD_CONST              51 (('bot',))
           1414 IMPORT_NAME              8 (data)
           1417 IMPORT_FROM             33 (bot)
           1420 STORE_FAST              14 (bot)
           1423 POP_TOP             

154        1424 LOAD_FAST               14 (bot)
           1427 LOAD_ATTR               33 (bot)
           1430 CALL_FUNCTION            0
           1433 POP_TOP             

155        1434 LOAD_FAST                0 (self)
           1437 LOAD_ATTR               13 (backk)
           1440 CALL_FUNCTION            0
           1443 POP_TOP             
           1444 JUMP_FORWARD           550 (to 1997)

157     >> 1447 LOAD_FAST                0 (self)
           1450 LOAD_ATTR                5 (asw)
           1453 LOAD_CONST              52 ('12')
           1456 COMPARE_OP               2 (==)
           1459 POP_JUMP_IF_FALSE     1501

158        1462 LOAD_CONST               6 (-1)
           1465 LOAD_CONST              53 (('yahoo_clone',))
           1468 IMPORT_NAME              8 (data)
           1471 IMPORT_FROM             34 (yahoo_clone)
           1474 STORE_FAST              15 (yahoo_clone)
           1477 POP_TOP             

159        1478 LOAD_FAST               15 (yahoo_clone)
           1481 LOAD_ATTR               35 (clon)
           1484 CALL_FUNCTION            0
           1487 POP_TOP             

160        1488 LOAD_FAST                0 (self)
           1491 LOAD_ATTR               13 (backk)
           1494 CALL_FUNCTION            0
           1497 POP_TOP             
           1498 JUMP_FORWARD           496 (to 1997)

162     >> 1501 LOAD_FAST                0 (self)
           1504 LOAD_ATTR                5 (asw)
           1507 LOAD_CONST              54 ('13')
           1510 COMPARE_OP               2 (==)
           1513 POP_JUMP_IF_FALSE     1555

163        1516 LOAD_CONST               6 (-1)
           1519 LOAD_CONST              55 (('app_check',))
           1522 IMPORT_NAME              8 (data)
           1525 IMPORT_FROM             36 (app_check)
           1528 STORE_FAST              16 (app_check)
           1531 POP_TOP             

164        1532 LOAD_FAST               16 (app_check)
           1535 LOAD_ATTR               37 (apps)
           1538 CALL_FUNCTION            0
           1541 POP_TOP             

165        1542 LOAD_FAST                0 (self)
           1545 LOAD_ATTR               13 (backk)
           1548 CALL_FUNCTION            0
           1551 POP_TOP             
           1552 JUMP_FORWARD           442 (to 1997)

167     >> 1555 LOAD_FAST                0 (self)
           1558 LOAD_ATTR                5 (asw)
           1561 LOAD_CONST              56 ('14')
           1564 COMPARE_OP               2 (==)
           1567 POP_JUMP_IF_FALSE     1599

168        1570 LOAD_CONST               6 (-1)
           1573 LOAD_CONST              57 (('listen',))
           1576 IMPORT_NAME              8 (data)
           1579 IMPORT_FROM             38 (listen)
           1582 STORE_FAST              17 (listen)
           1585 POP_TOP             

169        1586 LOAD_FAST               17 (listen)
           1589 LOAD_ATTR               38 (listen)
           1592 CALL_FUNCTION            0
           1595 POP_TOP             
           1596 JUMP_FORWARD           398 (to 1997)

171     >> 1599 LOAD_FAST                0 (self)
           1602 LOAD_ATTR                5 (asw)
           1605 LOAD_CONST              58 ('15')
           1608 COMPARE_OP               2 (==)
           1611 POP_JUMP_IF_FALSE     1666

172        1614 LOAD_CONST              59 ('[%s#%s] Updating Asu Toolkit ...')
           1617 LOAD_GLOBAL              1 (G)
           1620 LOAD_GLOBAL              3 (N)
           1623 BUILD_TUPLE              2
           1626 BINARY_MODULO       
           1627 PRINT_ITEM          
           1628 PRINT_NEWLINE       

173        1629 LOAD_GLOBAL             39 (os)
           1632 LOAD_ATTR               40 (system)
           1635 LOAD_CONST              60 ('git pull')
           1638 CALL_FUNCTION            1
           1641 POP_TOP             

174        1642 LOAD_CONST              61 ('%s[%s**%s]%s Asu was updated. \xc2\xaf\\_(\xe3\x83\x84)_/\xc2\xaf')
           1645 LOAD_GLOBAL              1 (G)
           1648 LOAD_GLOBAL              2 (R)
           1651 LOAD_GLOBAL              1 (G)
           1654 LOAD_GLOBAL              3 (N)
           1657 BUILD_TUPLE              4
           1660 BINARY_MODULO       
           1661 PRINT_ITEM          
           1662 PRINT_NEWLINE       
           1663 JUMP_FORWARD           331 (to 1997)

176     >> 1666 LOAD_FAST                0 (self)
           1669 LOAD_ATTR                5 (asw)
           1672 LOAD_CONST              62 ('16')
           1675 COMPARE_OP               2 (==)
           1678 POP_JUMP_IF_FALSE     1713

177        1681 LOAD_GLOBAL              6 (exit)
           1684 LOAD_CONST              63 ('%s[%s*%s%s]%s Bye \xc2\xaf\\_(\xe3\x83\x84)_/\xc2\xaf')
           1687 LOAD_GLOBAL             41 (C)
           1690 LOAD_GLOBAL              2 (R)
           1693 LOAD_GLOBAL              3 (N)
           1696 LOAD_GLOBAL             41 (C)
           1699 LOAD_GLOBAL              3 (N)
           1702 BUILD_TUPLE              5
           1705 BINARY_MODULO       
           1706 CALL_FUNCTION            1
           1709 POP_TOP             
           1710 JUMP_FORWARD           284 (to 1997)

179     >> 1713 LOAD_FAST                0 (self)
           1716 LOAD_ATTR                5 (asw)
           1719 LOAD_CONST              64 ('move')
           1722 COMPARE_OP               2 (==)
           1725 POP_JUMP_IF_FALSE     1764

180        1728 LOAD_GLOBAL             39 (os)
           1731 LOAD_ATTR               42 (remove)
           1734 LOAD_CONST              65 ('config/config.json')
           1737 CALL_FUNCTION            1
           1740 POP_TOP             

181        1741 LOAD_GLOBAL             39 (os)
           1744 LOAD_ATTR               43 (removedirs)
           1747 LOAD_CONST              66 ('config')
           1750 CALL_FUNCTION            1
           1753 POP_TOP             

182        1754 LOAD_GLOBAL             44 (login)
           1757 CALL_FUNCTION            0
           1760 POP_TOP             
           1761 JUMP_FORWARD           233 (to 1997)

184     >> 1764 LOAD_FAST                0 (self)
           1767 LOAD_ATTR                5 (asw)
           1770 LOAD_CONST              67 ('banner')
           1773 COMPARE_OP               2 (==)
           1776 POP_JUMP_IF_FALSE     1789

185        1779 LOAD_GLOBAL             45 (ASU)
           1782 CALL_FUNCTION            0
           1785 POP_TOP             
           1786 JUMP_FORWARD           208 (to 1997)

187     >> 1789 LOAD_FAST                0 (self)
           1792 LOAD_ATTR                5 (asw)
           1795 LOAD_CONST              68 ('0')
           1798 COMPARE_OP               2 (==)
           1801 POP_JUMP_IF_TRUE      1819
           1804 LOAD_FAST                0 (self)
           1807 LOAD_ATTR                5 (asw)
           1810 LOAD_CONST              69 ('00')
           1813 COMPARE_OP               2 (==)
           1816 POP_JUMP_IF_FALSE     1848

188     >> 1819 LOAD_CONST               6 (-1)
           1822 LOAD_CONST              70 (('inf',))
           1825 IMPORT_NAME              8 (data)
           1828 IMPORT_FROM             46 (inf)
           1831 STORE_FAST              18 (inf)
           1834 POP_TOP             

189        1835 LOAD_FAST               18 (inf)
           1838 LOAD_ATTR               47 (buddy)
           1841 CALL_FUNCTION            0
           1844 POP_TOP             
           1845 JUMP_FORWARD           149 (to 1997)

191     >> 1848 LOAD_FAST                0 (self)
           1851 LOAD_ATTR                5 (asw)
           1854 LOAD_CONST              71 ('17')
           1857 COMPARE_OP               2 (==)
           1860 POP_JUMP_IF_FALSE     1892

192        1863 LOAD_CONST               6 (-1)
           1866 LOAD_CONST              72 (('reg',))
           1869 IMPORT_NAME              8 (data)
           1872 IMPORT_FROM             48 (reg)
           1875 STORE_FAST              19 (reg)
           1878 POP_TOP             

193        1879 LOAD_FAST               19 (reg)
           1882 LOAD_ATTR               48 (reg)
           1885 CALL_FUNCTION            0
           1888 POP_TOP             
           1889 JUMP_FORWARD           105 (to 1997)

195     >> 1892 LOAD_FAST                0 (self)
           1895 LOAD_ATTR                5 (asw)
           1898 LOAD_CONST              73 ('99')
           1901 COMPARE_OP               2 (==)
           1904 POP_JUMP_IF_FALSE     1932

196        1907 LOAD_GLOBAL             49 (subprocess)
           1910 LOAD_ATTR               50 (check_output)
           1913 LOAD_CONST              74 ('am')
           1916 LOAD_CONST              75 ('start')
           1919 LOAD_CONST              76 ('https://youtu.be/bi1X8o_BGsk')
           1922 BUILD_LIST               3
           1925 CALL_FUNCTION            1
           1928 POP_TOP             
           1929 JUMP_FORWARD            65 (to 1997)

198     >> 1932 LOAD_FAST                0 (self)
           1935 LOAD_ATTR                5 (asw)
           1938 LOAD_CONST              77 ('88')
           1941 COMPARE_OP               2 (==)
           1944 POP_JUMP_IF_FALSE     1972

199        1947 LOAD_GLOBAL             49 (subprocess)
           1950 LOAD_ATTR               50 (check_output)
           1953 LOAD_CONST              74 ('am')
           1956 LOAD_CONST              75 ('start')
           1959 LOAD_CONST              78 ('https://api.whatsapp.com/send?phone=62895353484895')
           1962 BUILD_LIST               3
           1965 CALL_FUNCTION            1
           1968 POP_TOP             
           1969 JUMP_FORWARD            25 (to 1997)

201     >> 1972 LOAD_CONST              79 ('%s[!]%s Invalid Options!')
           1975 LOAD_GLOBAL              2 (R)
           1978 LOAD_GLOBAL              3 (N)
           1981 BUILD_TUPLE              2
           1984 BINARY_MODULO       
           1985 PRINT_ITEM          
           1986 PRINT_NEWLINE       

202        1987 LOAD_FAST                0 (self)
           1990 LOAD_ATTR                7 (choice)
           1993 CALL_FUNCTION            0
           1996 POP_TOP             
        >> 1997 LOAD_CONST               0 (None)
           2000 RETURN_VALUE        


Disassembly of con:
 12           0 LOAD_GLOBAL              0 (os)
              3 LOAD_ATTR                1 (path)
              6 LOAD_ATTR                2 (exists)
              9 LOAD_CONST               1 ('config')
             12 CALL_FUNCTION            1
             15 POP_JUMP_IF_FALSE       21

 13          18 JUMP_FORWARD            13 (to 34)

 15     >>   21 LOAD_GLOBAL              0 (os)
             24 LOAD_ATTR                3 (mkdir)
             27 LOAD_CONST               1 ('config')
             30 CALL_FUNCTION            1
             33 POP_TOP             
        >>   34 LOAD_CONST               0 (None)
             37 RETURN_VALUE        

Disassembly of login:
 19           0 LOAD_GLOBAL              0 (con)
              3 CALL_FUNCTION            0
              6 POP_TOP             

 20           7 LOAD_GLOBAL              1 (requests)
             10 LOAD_ATTR                2 (Session)
             13 CALL_FUNCTION            0
             16 STORE_FAST               0 (req)
             19 LOAD_FAST                0 (req)
             22 LOAD_ATTR                3 (headers)
             25 LOAD_ATTR                4 (update)
             28 BUILD_MAP                1
             31 LOAD_CONST               1 ('Mozilla/5.0 (Linux; Android 5.1; PICOphone_M4U_M2_M Build/LMY47D; wv) AppleWebKit/537.36 (KHTML, like Gecko) Version/4.0 Chrome/43.0.2357.121 Mobile Safari/537.36')
             34 LOAD_CONST               2 ('User-Agent')
             37 STORE_MAP           
             38 CALL_FUNCTION            1
             41 POP_TOP             

 21          42 LOAD_GLOBAL              5 (raw_input)
             45 LOAD_CONST               3 ('[!] No Account Detected\n[*] Login Your Fb\n[?] Username: ')
             48 CALL_FUNCTION            1
             51 STORE_FAST               1 (e)

 22          54 LOAD_GLOBAL              5 (raw_input)
             57 LOAD_CONST               4 ('[?] Password: ')
             60 CALL_FUNCTION            1
             63 STORE_FAST               2 (p)

 23          66 LOAD_CONST               5 ('[*] Login ...')
             69 PRINT_ITEM          
             70 PRINT_NEWLINE       

 24          71 LOAD_FAST                0 (req)
             74 LOAD_ATTR                6 (post)
             77 LOAD_CONST               6 ('https://mbasic.facebook.com/login')
             80 LOAD_CONST               7 ('data')
             83 BUILD_MAP                2
             86 LOAD_FAST                1 (e)
             89 LOAD_CONST               8 ('email')
             92 STORE_MAP           

 25          93 LOAD_FAST                2 (p)
             96 LOAD_CONST               9 ('pass')
             99 STORE_MAP           
            100 CALL_FUNCTION          257
            103 LOAD_ATTR                7 (url)
            106 STORE_FAST               3 (s)

 26         109 LOAD_CONST              10 ('save-device')
            112 LOAD_FAST                3 (s)
            115 COMPARE_OP               6 (in)
            118 POP_JUMP_IF_TRUE       133
            121 LOAD_CONST              11 ('m_sess')
            124 LOAD_FAST                3 (s)
            127 COMPARE_OP               6 (in)
            130 POP_JUMP_IF_FALSE      243

 27     >>  133 LOAD_GLOBAL              8 (json)
            136 LOAD_ATTR                9 (dumps)
            139 BUILD_MAP                3
            142 LOAD_FAST                1 (e)
            145 LOAD_CONST               8 ('email')
            148 STORE_MAP           

 28         149 LOAD_FAST                2 (p)
            152 LOAD_CONST               9 ('pass')
            155 STORE_MAP           

 29         156 LOAD_GLOBAL             10 (bs4)
            159 LOAD_ATTR               11 (BeautifulSoup)
            162 LOAD_FAST                0 (req)
            165 LOAD_ATTR               12 (get)
            168 LOAD_CONST              12 ('https://mbasic.facebook.com/me')
            171 CALL_FUNCTION            1
            174 LOAD_ATTR               13 (text)
            177 LOAD_CONST              13 ('features')
            180 LOAD_CONST              14 ('html.parser')
            183 CALL_FUNCTION          257
            186 LOAD_ATTR               14 (find)
            189 LOAD_CONST              15 ('title')
            192 CALL_FUNCTION            1
            195 LOAD_ATTR               13 (text)
            198 LOAD_CONST              16 ('name')
            201 STORE_MAP           
            202 CALL_FUNCTION            1
            205 STORE_FAST               4 (i)

 30         208 LOAD_GLOBAL             15 (open)
            211 LOAD_CONST              17 ('config/config.json')
            214 LOAD_CONST              18 ('w')
            217 CALL_FUNCTION            2
            220 LOAD_ATTR               16 (write)
            223 LOAD_FAST                4 (i)
            226 CALL_FUNCTION            1
            229 POP_TOP             

 31         230 LOAD_GLOBAL             17 (exit)
            233 LOAD_CONST              19 ('[*] Login Success..\n[!] Run again: python2 ASU.py')
            236 CALL_FUNCTION            1
            239 POP_TOP             
            240 JUMP_FORWARD             0 (to 243)

 33     >>  243 LOAD_CONST              20 ('checkpoint')
            246 LOAD_FAST                3 (s)
            249 COMPARE_OP               6 (in)
            252 POP_JUMP_IF_TRUE       267
            255 LOAD_CONST              21 ('challange')
            258 LOAD_FAST                3 (s)
            261 COMPARE_OP               6 (in)
            264 POP_JUMP_IF_FALSE      280

 34     >>  267 LOAD_GLOBAL             17 (exit)
            270 LOAD_CONST              22 ('[!] checkpoint challange,your account was locked by facebook,pls open your facebook in browser before you login with asu toolkit\n[!] Run again: python2 ASU.py')
            273 CALL_FUNCTION            1
            276 POP_TOP             
            277 JUMP_FORWARD            10 (to 290)

 36     >>  280 LOAD_GLOBAL             17 (exit)
            283 LOAD_CONST              23 ('[!] Login Failed.\n[!] Run again: python2 ASU.py')
            286 CALL_FUNCTION            1
            289 POP_TOP             
        >>  290 LOAD_CONST               0 (None)
            293 RETURN_VALUE        

